agnt5/__init__.py
agnt5/_compat.py
agnt5/_core.abi3.so
agnt5/_retry_utils.py
agnt5/_schema_utils.py
agnt5/_sentry.py
agnt5/_serialization.py
agnt5/_telemetry.py
agnt5/agent/__init__.py
agnt5/agent/context.py
agnt5/agent/core.py
agnt5/agent/decorator.py
agnt5/agent/events.py
agnt5/agent/handoff.py
agnt5/agent/registry.py
agnt5/agent/result.py
agnt5/checkpoint.py
agnt5/client.py
agnt5/context.py
agnt5/entity.py
agnt5/events.py
agnt5/exceptions.py
agnt5/function.py
agnt5/lm/__init__.py
agnt5/lm/base.py
agnt5/lm/client.py
agnt5/lm/events.py
agnt5/lm/types.py
agnt5/memoization.py
agnt5/memory.py
agnt5/tool.py
agnt5/tracing.py
agnt5/types.py
agnt5/version.py
agnt5/worker/__init__.py
agnt5/worker/_core.py
agnt5/worker/_executors.py
agnt5/worker/_utils.py
agnt5/workflow.py
agnt5-0.3.7.dist-info/METADATA
agnt5-0.3.7.dist-info/WHEEL
agnt5-0.3.7.dist-info/RECORD
