Metadata-Version: 2.4
Name: agnt5
Version: 0.3.7
Classifier: Development Status :: 3 - Alpha
Classifier: Intended Audience :: Developers
Classifier: Programming Language :: Python :: 3
Classifier: Programming Language :: Python :: 3.11
Classifier: Programming Language :: Python :: 3.12
Classifier: Programming Language :: Python :: 3.13
Classifier: Programming Language :: Python :: 3.14
Classifier: Programming Language :: Rust
Classifier: Operating System :: POSIX :: Linux
Classifier: Operating System :: MacOS
Classifier: Operating System :: Microsoft :: Windows
Requires-Dist: maturin>=1.9.3
Requires-Dist: docstring-parser>=0.15
Requires-Dist: typing-extensions>=4.8
Requires-Dist: httpx>=0.28.1
Requires-Dist: pydantic>=2.0
Requires-Dist: sentry-sdk>=2.0.0
Requires-Dist: edwh-uuid7>=0.2.3
Requires-Dist: orjson>=3.11.5
Summary: AGNT5 Python SDK - Build durable, resilient agent-first applications
Author-email: AGNT5 Team <team@agnt5.com>
License: Apache-2.0
Requires-Python: >=3.11
Project-URL: Documentation, https://agnt5.com/sdk/python
Project-URL: Homepage, https://agnt5.com
